<?xml version="1.0" encoding="utf-8"?>
<Dependencies>
  <Dependency>
    <ExtensionId>ivNet.BWCC</ExtensionId>
    <LoaderName>DynamicExtensionLoader</LoaderName>
    <VirtualPath>~/Themes/ivNet.BWCC/ivNet.BWCC.csproj</VirtualPath>
    <Hash>da94fe4babe764d8</Hash>
  </Dependency>
  <Dependency>
    <ExtensionId>ivNet.Club</ExtensionId>
    <LoaderName>PrecompiledExtensionLoader</LoaderName>
    <VirtualPath>~/Modules/ivNet.Club/bin/ivNet.Club.dll</VirtualPath>
    <Hash>dee153102838f8</Hash>
  </Dependency>
  <Dependency>
    <ExtensionId>Lucene</ExtensionId>
    <LoaderName>PrecompiledExtensionLoader</LoaderName>
    <VirtualPath>~/Modules/Lucene/bin/Lucene.dll</VirtualPath>
    <Hash>922b3b600cfed081</Hash>
  </Dependency>
  <Dependency>
    <ExtensionId>Markdown</ExtensionId>
    <LoaderName>PrecompiledExtensionLoader</LoaderName>
    <VirtualPath>~/Modules/Markdown/bin/Markdown.dll</VirtualPath>
    <Hash>923ef373f5afec0b</Hash>
  </Dependency>
  <Dependency>
    <ExtensionId>Orchard.Alias</ExtensionId>
    <LoaderName>PrecompiledExtensionLoader</LoaderName>
    <VirtualPath>~/Modules/Orchard.Alias/bin/Orchard.Alias.dll</VirtualPath>
    <Hash>48faa4e435b618c0</Hash>
  </Dependency>
  <Dependency>
    <ExtensionId>Orchard.AntiSpam</ExtensionId>
    <LoaderName>PrecompiledExtensionLoader</LoaderName>
    <VirtualPath>~/Modules/Orchard.AntiSpam/bin/Orchard.AntiSpam.dll</VirtualPath>
    <Hash>9258722ba832ab2c</Hash>
  </Dependency>
  <Dependency>
    <ExtensionId>Orchard.ArchiveLater</ExtensionId>
    <LoaderName>PrecompiledExtensionLoader</LoaderName>
    <VirtualPath>~/Modules/Orchard.ArchiveLater/bin/Orchard.ArchiveLater.dll</VirtualPath>
    <Hash>491224fbd72f608f</Hash>
  </Dependency>
  <Dependency>
    <ExtensionId>Orchard.Autoroute</ExtensionId>
    <LoaderName>PrecompiledExtensionLoader</LoaderName>
    <VirtualPath>~/Modules/Orchard.Autoroute/bin/Orchard.Autoroute.dll</VirtualPath>
    <Hash>dbabaf686d93c911</Hash>
  </Dependency>
  <Dependency>
    <ExtensionId>Orchard.Azure</ExtensionId>
    <LoaderName>PrecompiledExtensionLoader</LoaderName>
    <VirtualPath>~/Modules/Orchard.Azure/bin/Orchard.Azure.dll</VirtualPath>
    <Hash>be7404329f77cc1b</Hash>
  </Dependency>
  <Dependency>
    <ExtensionId>Orchard.Azure.MediaServices</ExtensionId>
    <LoaderName>PrecompiledExtensionLoader</LoaderName>
    <VirtualPath>~/Modules/Orchard.Azure.MediaServices/bin/Orchard.Azure.MediaServices.dll</VirtualPath>
    <Hash>742521d4c8cc0ae4</Hash>
  </Dependency>
  <Dependency>
    <ExtensionId>Orchard.Blogs</ExtensionId>
    <LoaderName>PrecompiledExtensionLoader</LoaderName>
    <VirtualPath>~/Modules/Orchard.Blogs/bin/Orchard.Blogs.dll</VirtualPath>
    <Hash>6e6559f5d672a2c5</Hash>
  </Dependency>
  <Dependency>
    <ExtensionId>Orchard.Caching</ExtensionId>
    <LoaderName>PrecompiledExtensionLoader</LoaderName>
    <VirtualPath>~/Modules/Orchard.Caching/bin/Orchard.Caching.dll</VirtualPath>
    <Hash>4900bcea92851293</Hash>
  </Dependency>
  <Dependency>
    <ExtensionId>Orchard.CodeGeneration</ExtensionId>
    <LoaderName>PrecompiledExtensionLoader</LoaderName>
    <VirtualPath>~/Modules/Orchard.CodeGeneration/bin/Orchard.CodeGeneration.dll</VirtualPath>
    <Hash>49188d022fa565ab</Hash>
  </Dependency>
  <Dependency>
    <ExtensionId>Orchard.Comments</ExtensionId>
    <LoaderName>PrecompiledExtensionLoader</LoaderName>
    <VirtualPath>~/Modules/Orchard.Comments/bin/Orchard.Comments.dll</VirtualPath>
    <Hash>25068cac7be3e36a</Hash>
  </Dependency>
  <Dependency>
    <ExtensionId>Orchard.ContentPermissions</ExtensionId>
    <LoaderName>PrecompiledExtensionLoader</LoaderName>
    <VirtualPath>~/Modules/Orchard.ContentPermissions/bin/Orchard.ContentPermissions.dll</VirtualPath>
    <Hash>6e78d2085e110617</Hash>
  </Dependency>
  <Dependency>
    <ExtensionId>Orchard.ContentPicker</ExtensionId>
    <LoaderName>PrecompiledExtensionLoader</LoaderName>
    <VirtualPath>~/Modules/Orchard.ContentPicker/bin/Orchard.ContentPicker.dll</VirtualPath>
    <Hash>49161cffcc5d7915</Hash>
  </Dependency>
  <Dependency>
    <ExtensionId>Orchard.ContentTypes</ExtensionId>
    <LoaderName>PrecompiledExtensionLoader</LoaderName>
    <VirtualPath>~/Modules/Orchard.ContentTypes/bin/Orchard.ContentTypes.dll</VirtualPath>
    <Hash>92669a3a192dc15a</Hash>
  </Dependency>
  <Dependency>
    <ExtensionId>Orchard.CustomForms</ExtensionId>
    <LoaderName>PrecompiledExtensionLoader</LoaderName>
    <VirtualPath>~/Modules/Orchard.CustomForms/bin/Orchard.CustomForms.dll</VirtualPath>
    <Hash>25116cb783f81720</Hash>
  </Dependency>
  <Dependency>
    <ExtensionId>Orchard.DesignerTools</ExtensionId>
    <LoaderName>PrecompiledExtensionLoader</LoaderName>
    <VirtualPath>~/Modules/Orchard.DesignerTools/bin/Orchard.DesignerTools.dll</VirtualPath>
    <Hash>251ca4c383917eb9</Hash>
  </Dependency>
  <Dependency>
    <ExtensionId>Orchard.Email</ExtensionId>
    <LoaderName>PrecompiledExtensionLoader</LoaderName>
    <VirtualPath>~/Modules/Orchard.Email/bin/Orchard.Email.dll</VirtualPath>
    <Hash>24fb9ca188aa49f2</Hash>
  </Dependency>
  <Dependency>
    <ExtensionId>Orchard.Fields</ExtensionId>
    <LoaderName>PrecompiledExtensionLoader</LoaderName>
    <VirtualPath>~/Modules/Orchard.Fields/bin/Orchard.Fields.dll</VirtualPath>
    <Hash>48fe0ce7cd4a6e47</Hash>
  </Dependency>
  <Dependency>
    <ExtensionId>Orchard.Forms</ExtensionId>
    <LoaderName>PrecompiledExtensionLoader</LoaderName>
    <VirtualPath>~/Modules/Orchard.Forms/bin/Orchard.Forms.dll</VirtualPath>
    <Hash>48fb8ce4dc36640a</Hash>
  </Dependency>
  <Dependency>
    <ExtensionId>Orchard.ImageEditor</ExtensionId>
    <LoaderName>PrecompiledExtensionLoader</LoaderName>
    <VirtualPath>~/Modules/Orchard.ImageEditor/bin/Orchard.ImageEditor.dll</VirtualPath>
    <Hash>dbc8178522416f11</Hash>
  </Dependency>
  <Dependency>
    <ExtensionId>Orchard.ImportExport</ExtensionId>
    <LoaderName>PrecompiledExtensionLoader</LoaderName>
    <VirtualPath>~/Modules/Orchard.ImportExport/bin/Orchard.ImportExport.dll</VirtualPath>
    <Hash>49143cfdd2194ec8</Hash>
  </Dependency>
  <Dependency>
    <ExtensionId>Orchard.Indexing</ExtensionId>
    <LoaderName>PrecompiledExtensionLoader</LoaderName>
    <VirtualPath>~/Modules/Orchard.Indexing/bin/Orchard.Indexing.dll</VirtualPath>
    <Hash>490504eea2fa05d5</Hash>
  </Dependency>
  <Dependency>
    <ExtensionId>Orchard.JobsQueue</ExtensionId>
    <LoaderName>PrecompiledExtensionLoader</LoaderName>
    <VirtualPath>~/Modules/Orchard.JobsQueue/bin/Orchard.JobsQueue.dll</VirtualPath>
    <Hash>6e6671f66c2c7695</Hash>
  </Dependency>
  <Dependency>
    <ExtensionId>Orchard.jQuery</ExtensionId>
    <LoaderName>PrecompiledExtensionLoader</LoaderName>
    <VirtualPath>~/Modules/Orchard.jQuery/bin/Orchard.jQuery.dll</VirtualPath>
    <Hash>48ff54e90145241a</Hash>
  </Dependency>
  <Dependency>
    <ExtensionId>Orchard.Lists</ExtensionId>
    <LoaderName>PrecompiledExtensionLoader</LoaderName>
    <VirtualPath>~/Modules/Orchard.Lists/bin/Orchard.Lists.dll</VirtualPath>
    <Hash>48fbcce5841316dd</Hash>
  </Dependency>
  <Dependency>
    <ExtensionId>Orchard.Localization</ExtensionId>
    <LoaderName>PrecompiledExtensionLoader</LoaderName>
    <VirtualPath>~/Modules/Orchard.Localization/bin/Orchard.Localization.dll</VirtualPath>
    <Hash>49129cfc5da53486</Hash>
  </Dependency>
  <Dependency>
    <ExtensionId>Orchard.Media</ExtensionId>
    <LoaderName>PrecompiledExtensionLoader</LoaderName>
    <VirtualPath>~/Modules/Orchard.Media/bin/Orchard.Media.dll</VirtualPath>
    <Hash>923cf371d7fa39f6</Hash>
  </Dependency>
  <Dependency>
    <ExtensionId>Orchard.MediaLibrary</ExtensionId>
    <LoaderName>PrecompiledExtensionLoader</LoaderName>
    <VirtualPath>~/Modules/Orchard.MediaLibrary/bin/Orchard.MediaLibrary.dll</VirtualPath>
    <Hash>926532384d05b3f8</Hash>
  </Dependency>
  <Dependency>
    <ExtensionId>Orchard.MediaPicker</ExtensionId>
    <LoaderName>PrecompiledExtensionLoader</LoaderName>
    <VirtualPath>~/Modules/Orchard.MediaPicker/bin/Orchard.MediaPicker.dll</VirtualPath>
    <Hash>db9f78be3b31a042</Hash>
  </Dependency>
  <Dependency>
    <ExtensionId>Orchard.MediaProcessing</ExtensionId>
    <LoaderName>PrecompiledExtensionLoader</LoaderName>
    <VirtualPath>~/Modules/Orchard.MediaProcessing/bin/Orchard.MediaProcessing.dll</VirtualPath>
    <Hash>250d7e1547b74a61</Hash>
  </Dependency>
  <Dependency>
    <ExtensionId>Orchard.Migrations</ExtensionId>
    <LoaderName>PrecompiledExtensionLoader</LoaderName>
    <VirtualPath>~/Modules/Orchard.Migrations/bin/Orchard.Migrations.dll</VirtualPath>
    <Hash>490c3cf5ee98df78</Hash>
  </Dependency>
  <Dependency>
    <ExtensionId>Orchard.Modules</ExtensionId>
    <LoaderName>PrecompiledExtensionLoader</LoaderName>
    <VirtualPath>~/Modules/Orchard.Modules/bin/Orchard.Modules.dll</VirtualPath>
    <Hash>49021cebae233a01</Hash>
  </Dependency>
  <Dependency>
    <ExtensionId>Orchard.MultiTenancy</ExtensionId>
    <LoaderName>PrecompiledExtensionLoader</LoaderName>
    <VirtualPath>~/Modules/Orchard.MultiTenancy/bin/Orchard.MultiTenancy.dll</VirtualPath>
    <Hash>49133cfd16c926ec</Hash>
  </Dependency>
  <Dependency>
    <ExtensionId>Orchard.OutputCache</ExtensionId>
    <LoaderName>PrecompiledExtensionLoader</LoaderName>
    <VirtualPath>~/Modules/Orchard.OutputCache/bin/Orchard.OutputCache.dll</VirtualPath>
    <Hash>490f7cf928a16335</Hash>
  </Dependency>
  <Dependency>
    <ExtensionId>Orchard.Packaging</ExtensionId>
    <LoaderName>PrecompiledExtensionLoader</LoaderName>
    <VirtualPath>~/Modules/Orchard.Packaging/bin/Orchard.Packaging.dll</VirtualPath>
    <Hash>925dda3120345b61</Hash>
  </Dependency>
  <Dependency>
    <ExtensionId>Orchard.Pages</ExtensionId>
    <LoaderName>PrecompiledExtensionLoader</LoaderName>
    <VirtualPath>~/Modules/Orchard.Pages/bin/Orchard.Pages.dll</VirtualPath>
    <Hash>92653238b9a40c5b</Hash>
  </Dependency>
  <Dependency>
    <ExtensionId>Orchard.Projections</ExtensionId>
    <LoaderName>PrecompiledExtensionLoader</LoaderName>
    <VirtualPath>~/Modules/Orchard.Projections/bin/Orchard.Projections.dll</VirtualPath>
    <Hash>dbb2d76f5cf1e8c8</Hash>
  </Dependency>
  <Dependency>
    <ExtensionId>Orchard.PublishLater</ExtensionId>
    <LoaderName>PrecompiledExtensionLoader</LoaderName>
    <VirtualPath>~/Modules/Orchard.PublishLater/bin/Orchard.PublishLater.dll</VirtualPath>
    <Hash>4912ccfc786af1fa</Hash>
  </Dependency>
  <Dependency>
    <ExtensionId>Orchard.Recipes</ExtensionId>
    <LoaderName>PrecompiledExtensionLoader</LoaderName>
    <VirtualPath>~/Modules/Orchard.Recipes/bin/Orchard.Recipes.dll</VirtualPath>
    <Hash>25068cad46905f8a</Hash>
  </Dependency>
  <Dependency>
    <ExtensionId>Orchard.Roles</ExtensionId>
    <LoaderName>PrecompiledExtensionLoader</LoaderName>
    <VirtualPath>~/Modules/Orchard.Roles/bin/Orchard.Roles.dll</VirtualPath>
    <Hash>24fc84a224b62fc0</Hash>
  </Dependency>
  <Dependency>
    <ExtensionId>Orchard.Rules</ExtensionId>
    <LoaderName>PrecompiledExtensionLoader</LoaderName>
    <VirtualPath>~/Modules/Orchard.Rules/bin/Orchard.Rules.dll</VirtualPath>
    <Hash>24fbdca229972105</Hash>
  </Dependency>
  <Dependency>
    <ExtensionId>Orchard.Scripting</ExtensionId>
    <LoaderName>PrecompiledExtensionLoader</LoaderName>
    <VirtualPath>~/Modules/Orchard.Scripting/bin/Orchard.Scripting.dll</VirtualPath>
    <Hash>4908ecf27ee085ec</Hash>
  </Dependency>
  <Dependency>
    <ExtensionId>Orchard.Scripting.CSharp</ExtensionId>
    <LoaderName>PrecompiledExtensionLoader</LoaderName>
    <VirtualPath>~/Modules/Orchard.Scripting.CSharp/bin/Orchard.Scripting.CSharp.dll</VirtualPath>
    <Hash>6e68b9f337b26aee</Hash>
  </Dependency>
  <Dependency>
    <ExtensionId>Orchard.Scripting.Dlr</ExtensionId>
    <LoaderName>PrecompiledExtensionLoader</LoaderName>
    <VirtualPath>~/Modules/Orchard.Scripting.Dlr/bin/Orchard.Scripting.Dlr.dll</VirtualPath>
    <Hash>156e3a28f6e2d06</Hash>
  </Dependency>
  <Dependency>
    <ExtensionId>Orchard.Search</ExtensionId>
    <LoaderName>PrecompiledExtensionLoader</LoaderName>
    <VirtualPath>~/Modules/Orchard.Search/bin/Orchard.Search.dll</VirtualPath>
    <Hash>dbb777746724025e</Hash>
  </Dependency>
  <Dependency>
    <ExtensionId>Orchard.SecureSocketsLayer</ExtensionId>
    <LoaderName>PrecompiledExtensionLoader</LoaderName>
    <VirtualPath>~/Modules/Orchard.SecureSocketsLayer/bin/Orchard.SecureSocketsLayer.dll</VirtualPath>
    <Hash>492755112cfa6263</Hash>
  </Dependency>
  <Dependency>
    <ExtensionId>Orchard.Setup</ExtensionId>
    <LoaderName>PrecompiledExtensionLoader</LoaderName>
    <VirtualPath>~/Modules/Orchard.Setup/bin/Orchard.Setup.dll</VirtualPath>
    <Hash>6e56a9e72e07b77f</Hash>
  </Dependency>
  <Dependency>
    <ExtensionId>Orchard.Tags</ExtensionId>
    <LoaderName>PrecompiledExtensionLoader</LoaderName>
    <VirtualPath>~/Modules/Orchard.Tags/bin/Orchard.Tags.dll</VirtualPath>
    <Hash>24f7bc9e3e26de59</Hash>
  </Dependency>
  <Dependency>
    <ExtensionId>Orchard.TaskLease</ExtensionId>
    <LoaderName>PrecompiledExtensionLoader</LoaderName>
    <VirtualPath>~/Modules/Orchard.TaskLease/bin/Orchard.TaskLease.dll</VirtualPath>
    <Hash>49083cf1e6d5042f</Hash>
  </Dependency>
  <Dependency>
    <ExtensionId>Orchard.Taxonomies</ExtensionId>
    <LoaderName>PrecompiledExtensionLoader</LoaderName>
    <VirtualPath>~/Modules/Orchard.Taxonomies/bin/Orchard.Taxonomies.dll</VirtualPath>
    <Hash>250c7cb32aa4d168</Hash>
  </Dependency>
  <Dependency>
    <ExtensionId>Orchard.Templates</ExtensionId>
    <LoaderName>PrecompiledExtensionLoader</LoaderName>
    <VirtualPath>~/Modules/Orchard.Templates/bin/Orchard.Templates.dll</VirtualPath>
    <Hash>dbaec76bbd79baea</Hash>
  </Dependency>
  <Dependency>
    <ExtensionId>Orchard.Themes</ExtensionId>
    <LoaderName>PrecompiledExtensionLoader</LoaderName>
    <VirtualPath>~/Modules/Orchard.Themes/bin/Orchard.Themes.dll</VirtualPath>
    <Hash>48fe84e8159fe2d1</Hash>
  </Dependency>
  <Dependency>
    <ExtensionId>Orchard.Tokens</ExtensionId>
    <LoaderName>PrecompiledExtensionLoader</LoaderName>
    <VirtualPath>~/Modules/Orchard.Tokens/bin/Orchard.Tokens.dll</VirtualPath>
    <Hash>48fef4e84503e7c5</Hash>
  </Dependency>
  <Dependency>
    <ExtensionId>Orchard.Users</ExtensionId>
    <LoaderName>PrecompiledExtensionLoader</LoaderName>
    <VirtualPath>~/Modules/Orchard.Users/bin/Orchard.Users.dll</VirtualPath>
    <Hash>48fbe4e578e274e0</Hash>
  </Dependency>
  <Dependency>
    <ExtensionId>Orchard.Warmup</ExtensionId>
    <LoaderName>PrecompiledExtensionLoader</LoaderName>
    <VirtualPath>~/Modules/Orchard.Warmup/bin/Orchard.Warmup.dll</VirtualPath>
    <Hash>48ff34e8c7425863</Hash>
  </Dependency>
  <Dependency>
    <ExtensionId>Orchard.Widgets</ExtensionId>
    <LoaderName>PrecompiledExtensionLoader</LoaderName>
    <VirtualPath>~/Modules/Orchard.Widgets/bin/Orchard.Widgets.dll</VirtualPath>
    <Hash>dbb1ff6eff546962</Hash>
  </Dependency>
  <Dependency>
    <ExtensionId>Orchard.Workflows</ExtensionId>
    <LoaderName>PrecompiledExtensionLoader</LoaderName>
    <VirtualPath>~/Modules/Orchard.Workflows/bin/Orchard.Workflows.dll</VirtualPath>
    <Hash>dbacc768f765d93c</Hash>
  </Dependency>
  <Dependency>
    <ExtensionId>PJS.Bootstrap</ExtensionId>
    <LoaderName>DynamicExtensionLoader</LoaderName>
    <VirtualPath>~/Themes/PJS.Bootstrap/PJS.Bootstrap.csproj</VirtualPath>
    <Hash>a98f6bbb07fa6f55</Hash>
  </Dependency>
  <Dependency>
    <ExtensionId>SysCache</ExtensionId>
    <LoaderName>PrecompiledExtensionLoader</LoaderName>
    <VirtualPath>~/Modules/SysCache/bin/SysCache.dll</VirtualPath>
    <Hash>9265ab9abde7676b</Hash>
  </Dependency>
  <Dependency>
    <ExtensionId>TinyMce</ExtensionId>
    <LoaderName>PrecompiledExtensionLoader</LoaderName>
    <VirtualPath>~/Modules/TinyMce/bin/TinyMce.dll</VirtualPath>
    <Hash>48e994d363338ab6</Hash>
  </Dependency>
  <Dependency>
    <ExtensionId>Upgrade</ExtensionId>
    <LoaderName>PrecompiledExtensionLoader</LoaderName>
    <VirtualPath>~/Modules/Upgrade/bin/Upgrade.dll</VirtualPath>
    <Hash>2652215c52d0113d</Hash>
  </Dependency>
</Dependencies>